setup.py
paop/__init__.py
paop.egg-info/PKG-INFO
paop.egg-info/SOURCES.txt
paop.egg-info/dependency_links.txt
paop.egg-info/top_level.txt