Metadata-Version: 1.1
Name: paop
Version: 0.1.0
Summary: Python AOP framework
Home-page: https://github.com/stanislavfeldman/paop
Author: Stanislav Feldman
Author-email: UNKNOWN
License: UNKNOWN
Keywords: aop
Platform: UNKNOWN
Classifier: Topic :: Software Development
